kurra/__init__.py
kurra/file.py
kurra/shacl.py
kurra/sparql.py
kurra/utils.py
kurra/cli/__init__.py
kurra/cli/app.py
kurra/cli/console.py
kurra/cli/utils.py
kurra/cli/commands/__init__.py
kurra/cli/commands/file.py
kurra/cli/commands/shacl.py
kurra/cli/commands/sparql.py
kurra/cli/commands/db/__init__.py
kurra/cli/commands/db/fuseki.py
kurra/cli/commands/db/gsp.py
kurra/cli/commands/db/olis.py
kurra/db/fuseki.py
kurra/db/gsp.py
kurra/db/ogf.py
kurra/db/sparql.py
kurra-2.2.3.dist-info/METADATA
kurra-2.2.3.dist-info/WHEEL
kurra-2.2.3.dist-info/entry_points.txt
kurra-2.2.3.dist-info/licenses/LICENSE
kurra-2.2.3.dist-info/RECORD
