Metadata-Version: 2.4
Name: kurra
Version: 2.2.3
Summary: A Python package of RDF data manipulation functions that can be called from the command line or other software
Project-URL: Homepage, https://github.com/kurrawong/kurra
Project-URL: Documentation, https://docs.kurrawong.ai/tools/kurra
Project-URL: Source, https://github.com/kurrawong/kurra
Project-URL: Changelog, https://github.com/Kurrawong/kurra/releases
Author-email: Edmond Chuc <edmond@kurrawong.ai>, Nicholas Car <nick@kurrawong.ai>
License-Expression: BSD-3-Clause
License-File: LICENSE
Classifier: Development Status :: 5 - Production/Stable
Classifier: Intended Audience :: Developers
Classifier: Intended Audience :: Information Technology
Classifier: License :: OSI Approved :: BSD License
Classifier: Operating System :: OS Independent
Classifier: Programming Language :: Python
Classifier: Programming Language :: Python :: 3
Classifier: Programming Language :: Python :: 3 :: Only
Classifier: Programming Language :: Python :: 3.10
Classifier: Programming Language :: Python :: 3.11
Classifier: Programming Language :: Python :: 3.12
Classifier: Programming Language :: Python :: 3.13
Classifier: Topic :: Internet
Classifier: Topic :: Software Development :: Libraries :: Python Modules
Requires-Python: >=3.12
Requires-Dist: httpx>=0.28.1
Requires-Dist: pyshacl==0.30.0
Requires-Dist: rdflib>=7.3.0
Requires-Dist: rich>=13.9.4
Requires-Dist: shacl-rules>=0.1.3
Requires-Dist: sparqlkit>=0.4.0
Requires-Dist: typer>=0.15.1
Provides-Extra: dataframe
Requires-Dist: pandas>=2.3.3; extra == 'dataframe'
